README.md
setup.cfg
setup.py
coppertop_bones_dm.egg-info/PKG-INFO
coppertop_bones_dm.egg-info/SOURCES.txt
coppertop_bones_dm.egg-info/dependency_links.txt
coppertop_bones_dm.egg-info/not-zip-safe
coppertop_bones_dm.egg-info/requires.txt
coppertop_bones_dm.egg-info/top_level.txt
dm/_irange.py
dm/_range.py
dm/canvas.py
dm/distributions.py
dm/flux.py
dm/fs.py
dm/numpy.py
dm/ols.py
dm/p9.py
dm/pandaframe.py
dm/plotting.py
dm/pmf.py
dm/polarframe.py
dm/pp.py
dm/rates.py
dm/repl.py
dm/sequences.py
dm/testing.py
dm/wip.py
dm/_core/structs.py
dm/_core/types.py
dm/core/__init__.py
dm/core/aggman.py
dm/core/bones.py
dm/core/bones2.py
dm/core/comparisons.py
dm/core/contextual_scope.py
dm/core/conv.py
dm/core/datetime.py
dm/core/frame.py
dm/core/maths.py
dm/core/misc.py
dm/core/stats.py
dm/core/structs.py
dm/core/text.py
dm/core/types.py
dm/core/unicode.py
dm/finance/types.py
dm/frame/csv.py
dm/linalg/core.py
dm/linalg/orient.py
dm/linalg/types.py
dm/linalg/algos/underdetermined.py
dm/utils/countlines.py
dm/utils/testing.py