Metadata-Version: 2.4
Name: coppertop-bones-dm
Version: 2025.5.28
Summary: The dangermouse standard library for coppertop and bones
Home-page: https://github.com/coppertop-bones/dm
Download-URL: 
Author: David Briant
Author-email: dangermouseb@forwarding.cc
License: OSI Approved :: Apache Software License
Keywords: multiple,dispatch,piping,pipeline,pipe,functional,multimethods,multidispatch,functools,lambda,curry,currying,dataframe,polars,pandas
Classifier: Development Status :: 3 - Alpha
Classifier: Intended Audience :: Developers
Classifier: Intended Audience :: End Users/Desktop
Classifier: Intended Audience :: Science/Research
Classifier: Topic :: Utilities
Classifier: License :: OSI Approved :: Apache Software License
Classifier: Programming Language :: Python :: 3.11
Requires-Python: >=3.11
Requires-Dist: coppertop-bones==2025.5.28
Dynamic: author
Dynamic: author-email
Dynamic: classifier
Dynamic: description
Dynamic: description-content-type
Dynamic: home-page
Dynamic: keywords
Dynamic: license
Dynamic: requires-dist
Dynamic: requires-python
Dynamic: summary
